setup.py
viki/__init__.py
viki/fabric/__init__.py
viki/fabric/docker.py
viki/fabric/git.py
viki/fabric/helpers.py
viki_fabric_helpers.egg-info/PKG-INFO
viki_fabric_helpers.egg-info/SOURCES.txt
viki_fabric_helpers.egg-info/dependency_links.txt
viki_fabric_helpers.egg-info/requires.txt
viki_fabric_helpers.egg-info/top_level.txt